{
  "sales": [
    {
      "2022": [
        {
          "id": 1,
          "sale": 108,
          "month": 1
        },

        {
          "id": 2,
          "sale": 18,
          "month": 2
        },

        {
          "id": 3,
          "sale": 40,
          "month": 3
        },
        {
          "id": 4,
          "sale": 40,
          "month": 4
        },
        {
          "id": 5,
          "sale": 40,
          "month": 5
        },
        {
          "id": 6,
          "sale": 40,
          "month": 6
        },
        {
          "id": 7,
          "sale": 40,
          "month": 7
        },
        {
          "id": 8,
          "sale": 40,
          "month": 8
        },
        {
          "id": 9,
          "sale": 40,
          "month": 9
        },
        {
          "id": 10,
          "sale": 40,
          "month": 10
        },
        {
          "id": 11,
          "sale": 40,
          "month": 11
        },
        {
          "id": 12,
          "sale": 40,
          "month": 12
        }
      ],

      "2023": [
        {
          "id": 1,
          "sale": 108,
          "month": 1
        },

        {
          "id": 2,
          "sale": 18,
          "month": 2
        },

        {
          "id": 3,
          "sale": 40,
          "month": 3
        },
        {
          "id": 4,
          "sale": 40,
          "month": 4
        },
        {
          "id": 5,
          "sale": 40,
          "month": 5
        },
        {
          "id": 6,
          "sale": 40,
          "month": 6
        },
        {
          "id": 7,
          "sale": 40,
          "month": 7
        },
        {
          "id": 8,
          "sale": 40,
          "month": 8
        },
        {
          "id": 9,
          "sale": 40,
          "month": 9
        },
        {
          "id": 10,
          "sale": 40,
          "month": 10
        },
        {
          "id": 11,
          "sale": 40,
          "month": 11
        },
        {
          "id": 12,
          "sale": 40,
          "month": 12
        }
      ]
    }
  ]
}
